bpmn_parser/__init__.py
bpmn_parser/_exclusive_gateway.py
bpmn_parser/_intermediate_catch_event.py
bpmn_parser/_sequence_flow.py
bpmn_parser/_service_task.py
bpmn_parser/_task.py
bpmn_parser/_user_task.py
bpmn_parser/exceptions.py
bpmn_parser/parser.py
bpmn_parser-1.0.16.dist-info/METADATA
bpmn_parser-1.0.16.dist-info/WHEEL
bpmn_parser-1.0.16.dist-info/RECORD
