Metadata-Version: 2.1
Name: bpmn_parser
Version: 1.0.16
Summary: A simple BPMN Parser implemented in Python
Author: Daniel Bailo
Author-email: danbailoufms@gmail.com
Requires-Python: >=3.9,<4.0
Classifier: Programming Language :: Python :: 3
Classifier: Programming Language :: Python :: 3.9
Classifier: Programming Language :: Python :: 3.10
Classifier: Programming Language :: Python :: 3.11
Classifier: Programming Language :: Python :: 3.12
Requires-Dist: lxml (>=5.3.0,<6.0.0)
Project-URL: Changelog, https://github.com/danbailo/bpmn-parser/releases
Project-URL: Documentation, https://danbailo.github.io/bpmn-parser/
Project-URL: Homepage, https://github.com/danbailo/bpmn-parser
Project-URL: Issues, https://github.com/danbailo/bpmn-parser/issues
Project-URL: Repository, https://github.com/danbailo/bpmn-parser
